microsoft/teams/devtools/__init__.py
microsoft/teams/devtools/devtools_plugin.py
microsoft/teams/devtools/event.py
microsoft/teams/devtools/page.py
microsoft/teams/devtools/routes/__init__.py
microsoft/teams/devtools/routes/context.py
microsoft/teams/devtools/routes/router.py
microsoft/teams/devtools/routes/v3/__init__.py
microsoft/teams/devtools/routes/v3/router.py
microsoft/teams/devtools/routes/v3/conversations/__init__.py
microsoft/teams/devtools/routes/v3/conversations/router.py
microsoft/teams/devtools/routes/v3/conversations/activities/__init__.py
microsoft/teams/devtools/routes/v3/conversations/activities/create.py
microsoft/teams/devtools/routes/v3/conversations/activities/router.py
microsoft/teams/devtools/web/icon.png
microsoft/teams/devtools/web/index.html
microsoft/teams/devtools/web/teams.png
microsoft/teams/devtools/web/assets/FluentSystemIcons-Filled-BNz-nPog.woff2
microsoft/teams/devtools/web/assets/FluentSystemIcons-Filled-BkKNRAuh.ttf
microsoft/teams/devtools/web/assets/FluentSystemIcons-Filled-CKlopXFJ.woff
microsoft/teams/devtools/web/assets/FluentSystemIcons-Light-CPYKaotZ.ttf
microsoft/teams/devtools/web/assets/FluentSystemIcons-Light-DzHdd4FE.woff
microsoft/teams/devtools/web/assets/FluentSystemIcons-Light-eu0dDZrh.woff2
microsoft/teams/devtools/web/assets/FluentSystemIcons-Regular-Ck4JqYAr.ttf
microsoft/teams/devtools/web/assets/FluentSystemIcons-Regular-DG6j5pl_.woff
microsoft/teams/devtools/web/assets/FluentSystemIcons-Regular-DaURWknX.woff2
microsoft/teams/devtools/web/assets/FluentSystemIcons-Resizable-CnnvCM7P.ttf
microsoft/teams/devtools/web/assets/FluentSystemIcons-Resizable-DnCkRnj_.woff
microsoft/teams/devtools/web/assets/FluentSystemIcons-Resizable-Iep0utY8.woff2
microsoft/teams/devtools/web/assets/index-B_doQf7e.js
microsoft/teams/devtools/web/assets/index-DG9gkHg0.js
microsoft/teams/devtools/web/assets/index-DUmBwYhV.css
microsoft_teams_devtools-2.0.0a5.dist-info/METADATA
microsoft_teams_devtools-2.0.0a5.dist-info/WHEEL
microsoft_teams_devtools-2.0.0a5.dist-info/RECORD
