Metadata-Version: 2.4
Name: microsoft-teams-devtools
Version: 2.0.0a5
Summary: Local tool to streamline testing and development
Project-URL: Homepage, https://github.com/microsoft/teams.py/tree/main/packages/devtools/src/microsoft/teams/devtools
Author-email: Microsoft <TeamsAISDKFeedback@microsoft.com>
License-Expression: MIT
Keywords: agents,ai,bot,microsoft,teams
Requires-Python: <3.14,>=3.12
Requires-Dist: fastapi>=0.115.13
Requires-Dist: microsoft-teams-api
Requires-Dist: microsoft-teams-apps
Requires-Dist: pydantic>=2.0.0
Requires-Dist: uvicorn[standard]>=0.34.3
